TableAPI/__init__.py
TableAPI-1.1.5.dist-info/LICENSE
TableAPI-1.1.5.dist-info/METADATA
TableAPI-1.1.5.dist-info/WHEEL
TableAPI-1.1.5.dist-info/top_level.txt
TableAPI-1.1.5.dist-info/RECORD
