Metadata-Version: 2.1
Name: TableAPI
Version: 1.1.5
Summary: Create a simple table c:
Author-email: fluffy <me@fluffel.net>
Project-URL: Homepage, https://github.com/fluffeliger/tableapi
Project-URL: Bug Tracker, https://github.com/fluffeliger/tableapi/issues
Classifier: Programming Language :: Python :: 3
Classifier: License :: OSI Approved :: MIT License
Classifier: Operating System :: OS Independent
Requires-Python: >=3.7
License-File: LICENSE
